[
  {"cmd":"SS","title":"SS — Sell Segment","desc":"Boka upp given availability line (sälja plats).","example":"SS1C1","tags":["PNR","sell"],"category":"PNR"},
  {"cmd":"NM","title":"NM — Name Element","desc":"Lägg till passagerarnamn.","example":"NM1TURESSON/CONRI MR","tags":["PNR","names"],"category":"PNR"},
  {"cmd":"APM","title":"APM — Mobile","desc":"Lägg till mobilnummer i PNR.","example":"APM-0046792019653","tags":["PNR","contacts"],"category":"PNR"},
  {"cmd":"APE","title":"APE — Email","desc":"Lägg till e-postadress i PNR.","example":"APE-CONRI@MAIL.SE","tags":["PNR","contacts"],"category":"PNR"},
  {"cmd":"SR CTCM","title":"SR CTCM — Contact Mobile","desc":"Mobilnummer som SSR till flygbolaget.","example":"SRCTCM-00467071212121","tags":["PNR","SSR","contacts"],"category":"PNR"},
  {"cmd":"SR CTCE","title":"SR CTCE — Contact Email","desc":"E-postadress som SSR till flygbolaget.","example":"SRCTCE-anna//mail.se","tags":["PNR","SSR","contacts"],"category":"PNR"},
  {"cmd":"RM","title":"RM — Remark","desc":"Intern remark i PNR.","example":"RM TEST BOOKING","tags":["PNR","remarks"],"category":"PNR"},
  {"cmd":"RC","title":"RC — Confidential Remark","desc":"Dolt remark, syns ej på itinerary.","example":"RC INTERNAL ONLY","tags":["PNR","remarks"],"category":"PNR"},
  {"cmd":"RIR","title":"RIR — Itinerary Remark","desc":"Remark som visas på kundens itinerary.","example":"RIR Contact at gate","tags":["PNR","remarks"],"category":"PNR"},
  {"cmd":"TKTL","title":"TKTL — Ticketing Time Limit","desc":"Sätt biljettdeadline för bokning.","example":"TKTL25APR","tags":["PNR","ticketing"],"category":"PNR"},
  {"cmd":"ER","title":"ER — End and Retrieve","desc":"Spara bokning och få PNR-locator.","example":"ER","tags":["PNR","save"],"category":"PNR"},
  {"cmd":"IG","title":"IG — Ignore","desc":"Avbryt utan att spara ändringar.","example":"IG","tags":["PNR","safety"],"category":"PNR"},
  {"cmd":"RT","title":"RT — Retrieve PNR","desc":"Hämta sparad bokning.","example":"RT KZ6G63","tags":["PNR","retrieve"],"category":"PNR"},
  {"cmd":"SPX","title":"SPX — Split PNR","desc":"Splitta ut passagerare till ny PNR.","example":"SP3 → EF → ER","tags":["PNR","split"],"category":"PNR"},
  {"cmd":"EF","title":"EF — End Split","desc":"Bekräfta split och skapa AXR-länk.","example":"EF","tags":["PNR","split"],"category":"PNR"},
  {"cmd":"RRN","title":"RRN — Copy Seg+AP (no link)","desc":"Kopiera flygsträcka+AP rader utan länk.","example":"RRN/X","tags":["PNR","copy"],"category":"PNR"},
  {"cmd":"RRA","title":"RRA — Copy Segments (with link)","desc":"Kopiera flygsträcka och skapa länk mellan PNR.","example":"RRA/4","tags":["PNR","copy"],"category":"PNR"},
  {"cmd":"RRI","title":"RRI — Copy Segments (independent)","desc":"Kopiera segment utan länk.","example":"RRI/X","tags":["PNR","copy"],"category":"PNR"},
  {"cmd":"RRP","title":"RRP — Copy Passenger Data","desc":"Kopiera passagerardata mellan PNR.","example":"RRP/X","tags":["PNR","copy"],"category":"PNR"},
  {"cmd":"MS","title":"MS — Move to Line","desc":"Flytta markören till rad.","example":"MS 4","tags":["PNR","navigation"],"category":"PNR"},
  {"cmd":"GP","title":"GP — Move to Page","desc":"Hoppa till viss sida i PNR.","example":"GP INT","tags":["PNR","navigation"],"category":"PNR"},
  {"cmd":"MU/MD/MT/MB","title":"MU/MD/MT/MB — Navigation","desc":"Scrolla i PNR (up, down, top, bottom).","example":"MU","tags":["PNR","navigation"],"category":"PNR"},
  {"cmd":"NHP","title":"NHP — Missing Names/Seats","desc":"Felmeddelande: saknar namn/stolsinfo.","example":"NHP på HK-rad","tags":["PNR","error"],"category":"PNR"},
  {"cmd":"RMEFTERN","title":"RMEFTERN — Save under Surname","desc":"Spara PNR under efternamn för retrieval.","example":"RMTURESSON","tags":["PNR","save"],"category":"PNR"},
  {"cmd":"SIARNK","title":"SIARNK — Special Instruction","desc":"Instruktion vid hemresa från annan plats.","example":"SIARNK ARN","tags":["PNR","special"],"category":"PNR"}
]
